pymarketo/__init__.py
pymarketo-1.1.2.dist-info/DESCRIPTION.rst
pymarketo-1.1.2.dist-info/METADATA
pymarketo-1.1.2.dist-info/RECORD
pymarketo-1.1.2.dist-info/WHEEL
pymarketo-1.1.2.dist-info/metadata.json
pymarketo-1.1.2.dist-info/top_level.txt
