Metadata-Version: 2.0
Name: pymarketo
Version: 1.1.2
Summary: Python Client for the Marketo REST API
Home-page: https://github.com/osamakhn/pymarketo
Author: Osama Khan
Author-email: osamakhn@gmail.com
License: MIT License
Project-URL: Source, https://www.github.com/osamakhn/pymarketo
Keywords: Marketo REST API Wrapper Client
Platform: UNKNOWN
Requires-Dist: requests
Requires-Dist: marketorestpython
